<?xml version="1.0" encoding="utf-8"?>
<PAGINAS>
    <PAGINA><ID>1</ID><MODULO>A</MODULO><IDP1>MAP1</IDP1><TIPO1>0</TIPO1><IDP2></IDP2><TIPO2></TIPO2><IDP3></IDP3><TIPO3></TIPO3><IDP4></IDP4><TIPO4></TIPO4><IDP5></IDP5><TIPO5></TIPO5><IDP6></IDP6><TIPO6></TIPO6><IDP7></IDP7><TIPO7></TIPO7><IDP8></IDP8><TIPO8></TIPO8><IDP9></IDP9><TIPO9></TIPO9><IDP10></IDP10></PAGINA>
    <PAGINA><ID>2</ID><MODULO>B</MODULO><IDP1>MBP1</IDP1><TIPO1>1</TIPO1><IDP2>MBP2</IDP2><TIPO2>2</TIPO2><IDP3>MBP3</IDP3><TIPO3>3</TIPO3><IDP4>MBP4</IDP4><TIPO4>3</TIPO4><IDP5></IDP5><TIPO5></TIPO5><IDP6></IDP6><TIPO6></TIPO6><IDP7></IDP7><TIPO7></TIPO7><IDP8></IDP8><TIPO8></TIPO8><IDP9></IDP9><TIPO9></TIPO9><IDP10></IDP10></PAGINA>
    <PAGINA><ID>3</ID><MODULO>C</MODULO><IDP1>MCP1</IDP1><TIPO1>3</TIPO1><IDP2>MCP2</IDP2><TIPO2>3</TIPO2><IDP3>MCP3</IDP3><TIPO3>3</TIPO3><IDP4>MCP4</IDP4><TIPO4>3</TIPO4><IDP5>MCP5</IDP5><TIPO5>6</TIPO5><IDP6></IDP6><TIPO6></TIPO6><IDP7></IDP7><TIPO7></TIPO7><IDP8></IDP8><TIPO8></TIPO8><IDP9></IDP9><TIPO9></TIPO9><IDP10></IDP10></PAGINA>
    <PAGINA><ID>4</ID><MODULO>1</MODULO><IDP1>M1P1</IDP1><TIPO1>4</TIPO1><IDP2>M1P2</IDP2><TIPO2>4</TIPO2><IDP3>M1P3</IDP3><TIPO3>6</TIPO3><IDP4>M1P4</IDP4><TIPO4>6</TIPO4><IDP5>M1P5</IDP5><TIPO5>4</TIPO5><IDP6></IDP6><TIPO6></TIPO6><IDP7></IDP7><TIPO7></TIPO7><IDP8></IDP8><TIPO8></TIPO8><IDP9></IDP9><TIPO9></TIPO9><IDP10></IDP10></PAGINA>
    <PAGINA><ID>5</ID><MODULO>1</MODULO><IDP1>M1P7</IDP1><TIPO1>5</TIPO1><IDP2>M1P8</IDP2><TIPO2>6</TIPO2><IDP3>M1P9</IDP3><TIPO3>5</TIPO3><IDP4>M1P10</IDP4><TIPO4>5</TIPO4><IDP5></IDP5><TIPO5></TIPO5><IDP6></IDP6><TIPO6></TIPO6><IDP7></IDP7><TIPO7></TIPO7><IDP8></IDP8><TIPO8></TIPO8><IDP9></IDP9><TIPO9></TIPO9><IDP10></IDP10></PAGINA>
    <PAGINA><ID>6</ID><MODULO>1</MODULO><IDP1>M1P11</IDP1><TIPO1>6</TIPO1><IDP2>M1P12</IDP2><TIPO2>6</TIPO2><IDP3>M1P13</IDP3><TIPO3>5</TIPO3><IDP4>M1P14</IDP4><TIPO4>5</TIPO4><IDP5></IDP5><TIPO5></TIPO5><IDP6></IDP6><TIPO6></TIPO6><IDP7></IDP7><TIPO7></TIPO7><IDP8></IDP8><TIPO8></TIPO8><IDP9></IDP9><TIPO9></TIPO9><IDP10></IDP10></PAGINA>
    <PAGINA><ID>7</ID><MODULO>2</MODULO><IDP1>M2P1</IDP1><TIPO1>5</TIPO1><IDP2>M2P2</IDP2><TIPO2>6</TIPO2><IDP3>M2P3</IDP3><TIPO3>6</TIPO3><IDP4>M2P4</IDP4><TIPO4>4</TIPO4><IDP5>M2P5</IDP5><TIPO5>5</TIPO5><IDP6></IDP6><TIPO6></TIPO6><IDP7></IDP7><TIPO7></TIPO7><IDP8></IDP8><TIPO8></TIPO8><IDP9></IDP9><TIPO9></TIPO9><IDP10></IDP10></PAGINA>
    <PAGINA><ID>8</ID><MODULO>3</MODULO><IDP1>M3P1</IDP1><TIPO1>6</TIPO1><IDP2>M3P3</IDP2><TIPO2>5</TIPO2><IDP3>M3P4</IDP3><TIPO3>6</TIPO3><IDP4>M3P5</IDP4><TIPO4>4</TIPO4><IDP5></IDP5><TIPO5></TIPO5><IDP6></IDP6><TIPO6></TIPO6><IDP7></IDP7><TIPO7></TIPO7><IDP8></IDP8><TIPO8></TIPO8><IDP9></IDP9><TIPO9></TIPO9><IDP10></IDP10></PAGINA>
    <PAGINA><ID>9</ID><MODULO>4</MODULO><IDP1>M4P1</IDP1><TIPO1>5</TIPO1><IDP2>M4P2</IDP2><TIPO2>6</TIPO2><IDP3>M4P3</IDP3><TIPO3>5</TIPO3><IDP4>M4P4</IDP4><TIPO4>6</TIPO4><IDP5>M4P5</IDP5><TIPO5>6</TIPO5><IDP6></IDP6><TIPO6></TIPO6><IDP7></IDP7><TIPO7></TIPO7><IDP8></IDP8><TIPO8></TIPO8><IDP9></IDP9><TIPO9></TIPO9><IDP10></IDP10></PAGINA>
    <PAGINA><ID>10</ID><MODULO>4</MODULO><IDP1>M4P6</IDP1><TIPO1>4</TIPO1><IDP2>M4P7</IDP2><TIPO2>5</TIPO2><IDP3>M4P8</IDP3><TIPO3>5</TIPO3><IDP4>M4P9</IDP4><TIPO4>5</TIPO4><IDP5>M4P10</IDP5><TIPO5>6</TIPO5><IDP6></IDP6><TIPO6></TIPO6><IDP7></IDP7><TIPO7></TIPO7><IDP8></IDP8><TIPO8></TIPO8><IDP9></IDP9><TIPO9></TIPO9><IDP10></IDP10></PAGINA>
</PAGINAS>